MANIFEST.in
README.md
setup.py
laa/__init__.py
laa/tasks.py
laa/scripts/laa
lizards_are_awesome.egg-info/PKG-INFO
lizards_are_awesome.egg-info/SOURCES.txt
lizards_are_awesome.egg-info/dependency_links.txt
lizards_are_awesome.egg-info/not-zip-safe
lizards_are_awesome.egg-info/requires.txt
lizards_are_awesome.egg-info/top_level.txt