Metadata-Version: 1.1
Name: lizards-are-awesome
Version: 0.4.0
Summary: UNKNOWN
Home-page: https://github.com/furious-luke/lizards-are-awesome
Author: Luke Hodkinson
Author-email: furious.luke@gmail.com
License: BSD
Platform: UNKNOWN
Classifier: Development Status :: 3 - Alpha
Classifier: Intended Audience :: Developers
Classifier: License :: OSI Approved :: BSD License
Classifier: Natural Language :: English
Classifier: Operating System :: OS Independent
Classifier: Programming Language :: Python
